odoo/addons/product_dimension/README.rst
odoo/addons/product_dimension/__init__.py
odoo/addons/product_dimension/__manifest__.py
odoo/addons/product_dimension/i18n/ca.po
odoo/addons/product_dimension/i18n/de.po
odoo/addons/product_dimension/i18n/es.po
odoo/addons/product_dimension/i18n/fr.po
odoo/addons/product_dimension/i18n/fr_FR.po
odoo/addons/product_dimension/i18n/it.po
odoo/addons/product_dimension/i18n/product_dimension.pot
odoo/addons/product_dimension/i18n/pt.po
odoo/addons/product_dimension/models/__init__.py
odoo/addons/product_dimension/models/product_product.py
odoo/addons/product_dimension/models/product_template.py
odoo/addons/product_dimension/readme/CONTRIBUTORS.md
odoo/addons/product_dimension/readme/CREDITS.md
odoo/addons/product_dimension/readme/DESCRIPTION.md
odoo/addons/product_dimension/readme/HISTORY.md
odoo/addons/product_dimension/readme/USAGE.md
odoo/addons/product_dimension/static/description/icon.png
odoo/addons/product_dimension/static/description/index.html
odoo/addons/product_dimension/tests/__init__.py
odoo/addons/product_dimension/tests/test_compute_volume.py
odoo/addons/product_dimension/tests/test_template.py
odoo/addons/product_dimension/views/product_view.xml
odoo_addon_product_dimension-18.0.1.0.0.2.dist-info/METADATA
odoo_addon_product_dimension-18.0.1.0.0.2.dist-info/WHEEL
odoo_addon_product_dimension-18.0.1.0.0.2.dist-info/top_level.txt
odoo_addon_product_dimension-18.0.1.0.0.2.dist-info/RECORD
